pixiefairy/cli.py
pixiefairy/common.py
pixiefairy/config.py
pixiefairy/logic.py
pixiefairy/server.py
pixiefairy/webapp.py
pixiefairy-0.1.3.dist-info/METADATA
pixiefairy-0.1.3.dist-info/WHEEL
pixiefairy-0.1.3.dist-info/entry_points.txt
pixiefairy-0.1.3.dist-info/RECORD
