Metadata-Version: 2.1
Name: pixiefairy
Version: 0.1.3
Summary: Pixiefairy a Pixiecore API server companion
Home-page: https://github.com/mbovo/pixiefairy
License: Apache-2.0
Author: Manuel Bovo
Author-email: manuel.bovo@gmail.com
Requires-Python: >=3.10,<4.0
Classifier: License :: OSI Approved :: Apache Software License
Classifier: Programming Language :: Python :: 3
Classifier: Programming Language :: Python :: 3.10
Classifier: Programming Language :: Python :: 3.11
Requires-Dist: PyYAML (>=6.0,<7.0)
Requires-Dist: click (>=8.1.2,<9.0.0)
Requires-Dist: colorama (>=0.4.4,<0.5.0)
Requires-Dist: fastapi (>=0.75.2,<0.76.0)
Requires-Dist: gevent (>=21.12.0,<22.0.0)
Requires-Dist: loguru (>=0.6.0,<0.7.0)
Requires-Dist: pydantic-yaml (>=0.6.3,<0.7.0)
Requires-Dist: shellingham (>=1.4.0,<2.0.0)
Requires-Dist: typer (>=0.4.1,<0.5.0)
Requires-Dist: urllib3 (>=1.26.9,<2.0.0)
Requires-Dist: uvicorn (>=0.17.6,<0.18.0)
Project-URL: Repository, https://github.com/mbovo/pixiefairy
